seclibb/__init__.py
seclibb/main.py
seclibb/objects.py
seclibb-0.0.1.dist-info/LICENSE
seclibb-0.0.1.dist-info/METADATA
seclibb-0.0.1.dist-info/WHEEL
seclibb-0.0.1.dist-info/top_level.txt
seclibb-0.0.1.dist-info/RECORD
